crawl_agent/__init__.py
crawl_agent/helpers/__init__.py
crawl_agent/helpers/drssionpage.py
crawl_agent/helpers/manager.py
crawl_agent/utils/__init__.py
crawl_agent-0.1.2.dist-info/METADATA
crawl_agent-0.1.2.dist-info/WHEEL
crawl_agent-0.1.2.dist-info/RECORD
