Metadata-Version: 2.3
Name: crawl-agent
Version: 0.1.2
Summary: 
Author: gaozhe
Author-email: gaozhe@baiwang.com
Requires-Python: >=3.12,<3.15
Classifier: Programming Language :: Python :: 3
Classifier: Programming Language :: Python :: 3.12
Classifier: Programming Language :: Python :: 3.13
Requires-Dist: dataflow-sdk (>=0.1.9,<0.2.0)
Requires-Dist: drissionpage (>=4.1.0.18,<5.0.0.0)
Requires-Dist: jsonpath-ng (>=1.7.0,<2.0.0)
